{"nodes": [{"id": "evenstocks_agents_agents_risk_team_py", "label": "risk_team.py", "file_type": "code", "source_file": "evenstocks-agents\\agents\\risk_team.py", "source_location": "L1"}, {"id": "risk_team_riskagent", "label": "_RiskAgent", "file_type": "code", "source_file": "evenstocks-agents\\agents\\risk_team.py", "source_location": "L6"}, {"id": "baseagent", "label": "BaseAgent", "file_type": "code", "source_file": "", "source_location": ""}, {"id": "risk_team_riskagent_stance_description", "label": ".stance_description()", "file_type": "code", "source_file": "evenstocks-agents\\agents\\risk_team.py", "source_location": "L10"}, {"id": "risk_team_riskagent_system_prompt", "label": ".system_prompt()", "file_type": "code", "source_file": "evenstocks-agents\\agents\\risk_team.py", "source_location": "L13"}, {"id": "risk_team_riskagent_user_prompt", "label": ".user_prompt()", "file_type": "code", "source_file": "evenstocks-agents\\agents\\risk_team.py", "source_location": "L21"}, {"id": "risk_team_aggressiveriskanalyst", "label": "AggressiveRiskAnalyst", "file_type": "code", "source_file": "evenstocks-agents\\agents\\risk_team.py", "source_location": "L55"}, {"id": "risk_team_aggressiveriskanalyst_stance_description", "label": ".stance_description()", "file_type": "code", "source_file": "evenstocks-agents\\agents\\risk_team.py", "source_location": "L59"}, {"id": "risk_team_conservativeriskanalyst", "label": "ConservativeRiskAnalyst", "file_type": "code", "source_file": "evenstocks-agents\\agents\\risk_team.py", "source_location": "L66"}, {"id": "risk_team_conservativeriskanalyst_stance_description", "label": ".stance_description()", "file_type": "code", "source_file": "evenstocks-agents\\agents\\risk_team.py", "source_location": "L70"}, {"id": "risk_team_neutralriskanalyst", "label": "NeutralRiskAnalyst", "file_type": "code", "source_file": "evenstocks-agents\\agents\\risk_team.py", "source_location": "L77"}, {"id": "risk_team_neutralriskanalyst_stance_description", "label": ".stance_description()", "file_type": "code", "source_file": "evenstocks-agents\\agents\\risk_team.py", "source_location": "L81"}, {"id": "risk_team_riskmanager", "label": "RiskManager", "file_type": "code", "source_file": "evenstocks-agents\\agents\\risk_team.py", "source_location": "L88"}, {"id": "risk_team_riskmanager_system_prompt", "label": ".system_prompt()", "file_type": "code", "source_file": "evenstocks-agents\\agents\\risk_team.py", "source_location": "L94"}, {"id": "risk_team_riskmanager_user_prompt", "label": ".user_prompt()", "file_type": "code", "source_file": "evenstocks-agents\\agents\\risk_team.py", "source_location": "L100"}, {"id": "risk_team_rationale_1", "label": "Risk Team \u2014 3 risk analysts (aggressive, conservative, neutral) view the same da", "file_type": "rationale", "source_file": "evenstocks-agents\\agents\\risk_team.py", "source_location": "L1"}, {"id": "risk_team_rationale_89", "label": "Synthesizes 3 risk views into a final risk rating + sizing recommendation.", "file_type": "rationale", "source_file": "evenstocks-agents\\agents\\risk_team.py", "source_location": "L89"}], "edges": [{"source": "evenstocks_agents_agents_risk_team_py", "target": "evenstocks_agents_agents_base_py", "relation": "imports_from", "confidence": "EXTRACTED", "source_file": "evenstocks-agents\\agents\\risk_team.py", "source_location": "L3", "weight": 1.0}, {"source": "evenstocks_agents_agents_risk_team_py", "target": "risk_team_riskagent", "relation": "contains", "confidence": "EXTRACTED", "source_file": "evenstocks-agents\\agents\\risk_team.py", "source_location": "L6", "weight": 1.0}, {"source": "risk_team_riskagent", "target": "baseagent", "relation": "inherits", "confidence": "EXTRACTED", "source_file": "evenstocks-agents\\agents\\risk_team.py", "source_location": "L6", "weight": 1.0}, {"source": "risk_team_riskagent", "target": "risk_team_riskagent_stance_description", "relation": "method", "confidence": "EXTRACTED", "source_file": "evenstocks-agents\\agents\\risk_team.py", "source_location": "L10", "weight": 1.0}, {"source": "risk_team_riskagent", "target": "risk_team_riskagent_system_prompt", "relation": "method", "confidence": "EXTRACTED", "source_file": "evenstocks-agents\\agents\\risk_team.py", "source_location": "L13", "weight": 1.0}, {"source": "risk_team_riskagent", "target": "risk_team_riskagent_user_prompt", "relation": "method", "confidence": "EXTRACTED", "source_file": "evenstocks-agents\\agents\\risk_team.py", "source_location": "L21", "weight": 1.0}, {"source": "evenstocks_agents_agents_risk_team_py", "target": "risk_team_aggressiveriskanalyst", "relation": "contains", "confidence": "EXTRACTED", "source_file": "evenstocks-agents\\agents\\risk_team.py", "source_location": "L55", "weight": 1.0}, {"source": "risk_team_aggressiveriskanalyst", "target": "risk_team_riskagent", "relation": "inherits", "confidence": "EXTRACTED", "source_file": "evenstocks-agents\\agents\\risk_team.py", "source_location": "L55", "weight": 1.0}, {"source": "risk_team_aggressiveriskanalyst", "target": "risk_team_aggressiveriskanalyst_stance_description", "relation": "method", "confidence": "EXTRACTED", "source_file": "evenstocks-agents\\agents\\risk_team.py", "source_location": "L59", "weight": 1.0}, {"source": "evenstocks_agents_agents_risk_team_py", "target": "risk_team_conservativeriskanalyst", "relation": "contains", "confidence": "EXTRACTED", "source_file": "evenstocks-agents\\agents\\risk_team.py", "source_location": "L66", "weight": 1.0}, {"source": "risk_team_conservativeriskanalyst", "target": "risk_team_riskagent", "relation": "inherits", "confidence": "EXTRACTED", "source_file": "evenstocks-agents\\agents\\risk_team.py", "source_location": "L66", "weight": 1.0}, {"source": "risk_team_conservativeriskanalyst", "target": "risk_team_conservativeriskanalyst_stance_description", "relation": "method", "confidence": "EXTRACTED", "source_file": "evenstocks-agents\\agents\\risk_team.py", "source_location": "L70", "weight": 1.0}, {"source": "evenstocks_agents_agents_risk_team_py", "target": "risk_team_neutralriskanalyst", "relation": "contains", "confidence": "EXTRACTED", "source_file": "evenstocks-agents\\agents\\risk_team.py", "source_location": "L77", "weight": 1.0}, {"source": "risk_team_neutralriskanalyst", "target": "risk_team_riskagent", "relation": "inherits", "confidence": "EXTRACTED", "source_file": "evenstocks-agents\\agents\\risk_team.py", "source_location": "L77", "weight": 1.0}, {"source": "risk_team_neutralriskanalyst", "target": "risk_team_neutralriskanalyst_stance_description", "relation": "method", "confidence": "EXTRACTED", "source_file": "evenstocks-agents\\agents\\risk_team.py", "source_location": "L81", "weight": 1.0}, {"source": "evenstocks_agents_agents_risk_team_py", "target": "risk_team_riskmanager", "relation": "contains", "confidence": "EXTRACTED", "source_file": "evenstocks-agents\\agents\\risk_team.py", "source_location": "L88", "weight": 1.0}, {"source": "risk_team_riskmanager", "target": "baseagent", "relation": "inherits", "confidence": "EXTRACTED", "source_file": "evenstocks-agents\\agents\\risk_team.py", "source_location": "L88", "weight": 1.0}, {"source": "risk_team_riskmanager", "target": "risk_team_riskmanager_system_prompt", "relation": "method", "confidence": "EXTRACTED", "source_file": "evenstocks-agents\\agents\\risk_team.py", "source_location": "L94", "weight": 1.0}, {"source": "risk_team_riskmanager", "target": "risk_team_riskmanager_user_prompt", "relation": "method", "confidence": "EXTRACTED", "source_file": "evenstocks-agents\\agents\\risk_team.py", "source_location": "L100", "weight": 1.0}, {"source": "risk_team_riskagent_system_prompt", "target": "risk_team_neutralriskanalyst_stance_description", "relation": "calls", "confidence": "EXTRACTED", "source_file": "evenstocks-agents\\agents\\risk_team.py", "source_location": "L16", "weight": 1.0}, {"source": "risk_team_rationale_1", "target": "evenstocks_agents_agents_risk_team_py", "relation": "rationale_for", "confidence": "EXTRACTED", "source_file": "evenstocks-agents\\agents\\risk_team.py", "source_location": "L1", "weight": 1.0}, {"source": "risk_team_rationale_89", "target": "risk_team_riskmanager", "relation": "rationale_for", "confidence": "EXTRACTED", "source_file": "evenstocks-agents\\agents\\risk_team.py", "source_location": "L89", "weight": 1.0}]}